llama_index/storage/kvstore/dynamodb/__init__.py
llama_index/storage/kvstore/dynamodb/base.py
llama_index_storage_kvstore_dynamodb-0.4.1.dist-info/METADATA
llama_index_storage_kvstore_dynamodb-0.4.1.dist-info/WHEEL
llama_index_storage_kvstore_dynamodb-0.4.1.dist-info/licenses/LICENSE
llama_index_storage_kvstore_dynamodb-0.4.1.dist-info/RECORD
